solark_cloud/__init__.py
solark_cloud/api.py
solark_cloud/schemas.py
solark_cloud-0.0.3.dist-info/METADATA
solark_cloud-0.0.3.dist-info/WHEEL
solark_cloud-0.0.3.dist-info/licenses/LICENSE
solark_cloud-0.0.3.dist-info/RECORD
