Metadata-Version: 2.4
Name: solark_cloud
Version: 0.0.3
Summary: Fetch information from the Sol-Ark Cloud API
Project-URL: Homepage, https://github.com/zorkian/solark_cloud
Project-URL: Issues, https://github.com/zorkian/solark_cloud/issues
Author-email: Mark Smith <mark@qq.is>
License-File: LICENSE
Classifier: License :: OSI Approved :: MIT License
Classifier: Operating System :: OS Independent
Classifier: Programming Language :: Python :: 3
Requires-Python: >=3.8
Requires-Dist: requests
Requires-Dist: voluptuous
